setup.py
crange/__init__.py
crange/crange.py
crange/crtags.py
crange/options.py
crange/sourcefile.py
crange/tag.py
crange/tagdb.py
crange.egg-info/PKG-INFO
crange.egg-info/SOURCES.txt
crange.egg-info/dependency_links.txt
crange.egg-info/pbr.json
crange.egg-info/requires.txt
crange.egg-info/top_level.txt
crange/bin/crange
crange/bin/crtags