Metadata-Version: 1.1
Name: crange
Version: 0.1.3
Summary: Crange is a tool to index and cross-reference C/C++ source code.
Home-page: https://github.com/crange/crange
Author: Anurag Patel
Author-email: gnurag@gmail.com
License: BSD
Download-URL: https://github.com/crange/crange/releases
Keywords: crange,clang,llvm,parser,index,cross-reference,xref
Platform: UNKNOWN
Classifier: Intended Audience :: Developers
Classifier: Natural Language :: English
Classifier: Programming Language :: Python :: 2
